lp_lint_doctest/__init__.py
lp_lint_doctest/checkdoctest.py
lp_lint_doctest/reporter.py
lp_lint_doctest/tests/__init__.py
lp_lint_doctest/tests/test_doctest.py
lp_lint_doctest/tests/test_reporter.py
lp_lint_doctest-0.5.dist-info/LICENSE
lp_lint_doctest-0.5.dist-info/METADATA
lp_lint_doctest-0.5.dist-info/WHEEL
lp_lint_doctest-0.5.dist-info/entry_points.txt
lp_lint_doctest-0.5.dist-info/top_level.txt
lp_lint_doctest-0.5.dist-info/RECORD
