Metadata-Version: 2.1
Name: lp-lint-doctest
Version: 0.5
Summary: Style checker for Launchpad doctests.
Home-page: https://launchpad.net/lp-lint-doctest
Author: LAZR Developers
Author-email: lazr-developers@lists.launchpad.net
License: MIT
Classifier: Development Status :: 5 - Production/Stable
Classifier: Environment :: Console
Classifier: Intended Audience :: Developers
Classifier: License :: OSI Approved :: MIT License
Classifier: Programming Language :: Python
Classifier: Programming Language :: Python :: 3
Classifier: Programming Language :: Python :: 3.6
Classifier: Programming Language :: Python :: 3.7
Classifier: Programming Language :: Python :: 3.8
Classifier: Programming Language :: Python :: 3.9
Classifier: Programming Language :: Python :: 3.10
Classifier: Topic :: Software Development :: Quality Assurance
Requires-Python: >=3
License-File: LICENSE
Requires-Dist: pyflakes
Provides-Extra: test
Requires-Dist: testtools ; extra == 'test'
